fluaiagentsdk/__init__.py
fluaiagentsdk/agent.py
fluaaiagentsdk-1.0.9.dist-info/METADATA
fluaaiagentsdk-1.0.9.dist-info/WHEEL
fluaaiagentsdk-1.0.9.dist-info/top_level.txt
fluaaiagentsdk-1.0.9.dist-info/RECORD
