Metadata-Version: 2.1
Name: fluaaiagentsdk
Version: 1.0.9
Summary: SDK para integração com agentes da plataforma FluaAI
Home-page: https://github.com/GabrielFragaM/fluaai-agent-sdk
Author: Gabriel Fraga
Author-email: gabriellff130@gmail.com
Classifier: Programming Language :: Python :: 3
Classifier: License :: OSI Approved :: MIT License
Classifier: Operating System :: OS Independent
Requires-Python: >=3.7
Requires-Dist: aiohttp>=3.8.0
Requires-Dist: typing-extensions>=4.0.0
